reportmodifier/__init__.py
reportmodifier/__version__.py
reportmodifier/_file_tools.py
reportmodifier/_report_configuration.py
reportmodifier/ReportModifier.py
reportmodifier/ReportModifierVisitor.py
ReportModifierListener/__init__.py
ReportModifierListener/ReportModifierListener.py
robotframework_reportmodifier-0.2.8.dist-info/LICENSE
robotframework_reportmodifier-0.2.8.dist-info/METADATA
robotframework_reportmodifier-0.2.8.dist-info/WHEEL
robotframework_reportmodifier-0.2.8.dist-info/RECORD
