Metadata-Version: 2.1
Name: robotframework-reportmodifier
Version: 0.2.8
Summary: Filter report content.
Home-page: https://github.com/MarketSquare/robotframework-reportmodifier
Author: Matthias Gunther
Author-email: matthiasgunther@gmail.com
Requires-Python: >=3.8,<4.0
Classifier: Programming Language :: Python :: 3
Classifier: Programming Language :: Python :: 3.8
Classifier: Programming Language :: Python :: 3.9
Classifier: Programming Language :: Python :: 3.10
Classifier: Programming Language :: Python :: 3.11
Classifier: Programming Language :: Python :: 3.12
